Metadata-Version: 2.1
Name: yellowpages-business-scraper
Version: 1.0.0
Summary: A python library to scrape business data on yellowpages automatically.
Home-page: https://datakund.com
Author: DataKund
Author-email: datakund@gmail.com
License: Apache License 2.0
Keywords: yellowpages python bot_studio scraper data business info web-scraping
Platform: UNKNOWN
